[
	{
		"inputs": [
			{
				"internalType": "uint256",
				"name": "studentID",
				"type": "uint256"
			},
			{
				"internalType": "uint256",
				"name": "companyID",
				"type": "uint256"
			}
		],
		"name": "applyToCompany",
		"outputs": [],
		"stateMutability": "nonpayable",
		"type": "function"
	},
	{
		"inputs": [
			{
				"internalType": "string",
				"name": "_name",
				"type": "string"
			},
			{
				"internalType": "string",
				"name": "_description",
				"type": "string"
			}
		],
		"name": "createCompany",
		"outputs": [],
		"stateMutability": "nonpayable",
		"type": "function"
	},
	{
		"inputs": [
			{
				"internalType": "string",
				"name": "_name",
				"type": "string"
			},
			{
				"internalType": "string",
				"name": "_skills",
				"type": "string"
			},
			{
				"internalType": "uint256",
				"name": "_regid",
				"type": "uint256"
			}
		],
		"name": "createStudent",
		"outputs": [],
		"stateMutability": "nonpayable",
		"type": "function"
	},
	{
		"inputs": [
			{
				"internalType": "uint256",
				"name": "",
				"type": "uint256"
			}
		],
		"name": "companies",
		"outputs": [
			{
				"internalType": "uint256",
				"name": "companyID",
				"type": "uint256"
			},
			{
				"internalType": "string",
				"name": "name",
				"type": "string"
			},
			{
				"internalType": "string",
				"name": "description",
				"type": "string"
			}
		],
		"stateMutability": "view",
		"type": "function"
	},
	{
		"inputs": [
			{
				"internalType": "string",
				"name": "",
				"type": "string"
			}
		],
		"name": "complogin",
		"outputs": [
			{
				"internalType": "uint256",
				"name": "",
				"type": "uint256"
			}
		],
		"stateMutability": "view",
		"type": "function"
	},
	{
		"inputs": [
			{
				"internalType": "uint256",
				"name": "studentID",
				"type": "uint256"
			}
		],
		"name": "getStudentApplications",
		"outputs": [
			{
				"components": [
					{
						"internalType": "uint256",
						"name": "companyID",
						"type": "uint256"
					},
					{
						"internalType": "string",
						"name": "name",
						"type": "string"
					},
					{
						"internalType": "string",
						"name": "description",
						"type": "string"
					}
				],
				"internalType": "struct JobApplicationSystem.Company[]",
				"name": "",
				"type": "tuple[]"
			}
		],
		"stateMutability": "view",
		"type": "function"
	},
	{
		"inputs": [
			{
				"internalType": "uint256",
				"name": "",
				"type": "uint256"
			}
		],
		"name": "jobApplications",
		"outputs": [
			{
				"internalType": "uint256",
				"name": "studentID",
				"type": "uint256"
			},
			{
				"internalType": "uint256",
				"name": "companyID",
				"type": "uint256"
			}
		],
		"stateMutability": "view",
		"type": "function"
	},
	{
		"inputs": [],
		"name": "numApplications",
		"outputs": [
			{
				"internalType": "uint256",
				"name": "",
				"type": "uint256"
			}
		],
		"stateMutability": "view",
		"type": "function"
	},
	{
		"inputs": [],
		"name": "numCompanies",
		"outputs": [
			{
				"internalType": "uint256",
				"name": "",
				"type": "uint256"
			}
		],
		"stateMutability": "view",
		"type": "function"
	},
	{
		"inputs": [],
		"name": "numStudents",
		"outputs": [
			{
				"internalType": "uint256",
				"name": "",
				"type": "uint256"
			}
		],
		"stateMutability": "view",
		"type": "function"
	},
	{
		"inputs": [
			{
				"internalType": "uint256",
				"name": "",
				"type": "uint256"
			}
		],
		"name": "students",
		"outputs": [
			{
				"internalType": "uint256",
				"name": "studentID",
				"type": "uint256"
			},
			{
				"internalType": "string",
				"name": "name",
				"type": "string"
			},
			{
				"internalType": "string",
				"name": "skills",
				"type": "string"
			},
			{
				"internalType": "uint256",
				"name": "regid",
				"type": "uint256"
			}
		],
		"stateMutability": "view",
		"type": "function"
	},
	{
		"inputs": [
			{
				"internalType": "uint256",
				"name": "",
				"type": "uint256"
			}
		],
		"name": "studlogin",
		"outputs": [
			{
				"internalType": "uint256",
				"name": "",
				"type": "uint256"
			}
		],
		"stateMutability": "view",
		"type": "function"
	}
]